web_sdk/__init__.py
web_sdk/consts.py
web_sdk/enums.py
web_sdk/types.py
web_sdk/version.py
web_sdk/contrib/__init__.py
web_sdk/contrib/pydantic/__init__.py
web_sdk/contrib/pydantic/models.py
web_sdk/contrib/pydantic/utils.py
web_sdk/core/__init__.py
web_sdk/core/context.py
web_sdk/core/exceptions.py
web_sdk/core/kwargs.py
web_sdk/core/utils.py
web_sdk/core/backends/__init__.py
web_sdk/core/backends/httpx/__init__.py
web_sdk/core/backends/requests/__init__.py
web_sdk/core/backends/requests/sessions.py
web_sdk/core/backends/requests/settings.py
web_sdk/core/backends/requests/rest/__init__.py
web_sdk/core/backends/requests/rest/clients.py
web_sdk/core/backends/requests/rest/kwargs.py
web_sdk/core/backends/requests/rest/methods.py
web_sdk/core/backends/requests/rest/schemas.py
web_sdk/core/backends/requests/rest/services.py
web_sdk/core/backends/requests/soap/__init__.py
web_sdk/core/backends/requests/soap/clients.py
web_sdk/core/backends/requests/soap/kwargs.py
web_sdk/core/backends/requests/soap/methods.py
web_sdk/core/backends/requests/soap/services.py
web_sdk/core/backends/requests/soap/settings.py
web_sdk/core/bases/__init__.py
web_sdk/core/bases/clients.py
web_sdk/core/bases/methods.py
web_sdk/core/bases/services.py
web_sdk/core/bases/settings.py
web_sdk/core/bases/rest/__init__.py
web_sdk/core/bases/rest/clients.py
web_sdk/core/bases/rest/context.py
web_sdk/core/bases/rest/kwargs.py
web_sdk/core/bases/rest/methods.py
web_sdk/core/bases/rest/schemas.py
web_sdk/core/bases/soap/__init__.py
web_sdk/core/bases/soap/clients.py
web_sdk/core/bases/soap/context.py
web_sdk/core/bases/soap/files.py
web_sdk/core/bases/soap/kwargs.py
web_sdk/core/bases/soap/methods.py
web_sdk/core/bases/soap/schemas.py
web_sdk/core/bases/soap/settings.py
web_sdk/core/bases/soap/transports.py
web_sdk/core/fields/__init__.py
web_sdk/core/fields/fields.py
web_sdk/core/fields/parts.py
web_sdk/core/interfaces/__init__.py
web_sdk/core/interfaces/clients.py
web_sdk/core/interfaces/methods.py
web_sdk-0.1.3.dist-info/METADATA
web_sdk-0.1.3.dist-info/WHEEL
web_sdk-0.1.3.dist-info/licenses/LICENSE
web_sdk-0.1.3.dist-info/RECORD
