Metadata-Version: 2.4
Name: web-sdk
Version: 0.1.3
Summary: WebSDK is a library for quickly and easily creating SDKs for integration with third-party APIs.
Project-URL: Homepage, https://github.com/extralait-web/web-sdk
Project-URL: Documentation, https://github.com/extralait-web/web-sdk
Project-URL: Source, https://github.com/extralait-web/web-sdk
Project-URL: Issues, https://github.com/extralait-web/web-sdk/issues
Project-URL: Changelog, https://github.com/extralait-web/web-sdk/blob/master/CHANGELOG.md
Author-email: Abbakumov Valerii <tehnolog1999@gmail.com>
Maintainer-email: Abbakumov Valerii <tehnolog1999@gmail.com>
License-Expression: MIT
License-File: LICENSE
Keywords: api,extralait,rest,sdk,soap,web,web-api,web-sdk
Classifier: Development Status :: 3 - Alpha
Classifier: Framework :: Pydantic
Classifier: Framework :: Pydantic :: 2
Classifier: Intended Audience :: Developers
Classifier: Intended Audience :: Information Technology
Classifier: Operating System :: OS Independent
Classifier: Programming Language :: Python
Classifier: Programming Language :: Python :: 3
Classifier: Programming Language :: Python :: 3 :: Only
Classifier: Programming Language :: Python :: 3.10
Classifier: Programming Language :: Python :: 3.11
Classifier: Programming Language :: Python :: 3.12
Classifier: Programming Language :: Python :: 3.13
Classifier: Programming Language :: Python :: 3.14
Classifier: Programming Language :: Python :: Implementation :: CPython
Classifier: Programming Language :: Python :: Implementation :: PyPy
Classifier: Topic :: Internet
Classifier: Topic :: Software Development :: Libraries :: Python Modules
Requires-Python: >=3.10
Requires-Dist: pydantic-settings>=2.12.0
Requires-Dist: pydantic>=2.11.5
Requires-Dist: typing-extensions>=4.14.1
Requires-Dist: uuid>=1.30
Provides-Extra: rest
Requires-Dist: requests>=2.32.5; extra == 'rest'
Provides-Extra: soap
Requires-Dist: requests>=2.32.5; extra == 'soap'
Requires-Dist: zeep>=4.3.2; extra == 'soap'
Provides-Extra: xml
Requires-Dist: xmltodict>=1.0.2; extra == 'xml'
